wheel_matrix.py
wheel_matrix-0.4.0.dist-info/entry_points.txt
wheel_matrix-0.4.0.dist-info/licenses/LICENSE
wheel_matrix-0.4.0.dist-info/WHEEL
wheel_matrix-0.4.0.dist-info/METADATA
wheel_matrix-0.4.0.dist-info/RECORD
