Metadata-Version: 2.4
Name: wheel_matrix
Version: 0.4.0
Summary: Print a Markdown matrix of wheels.
Author-email: Daniel Pope <mauve@mauveweb.co.uk>
Requires-Python: >= 3.10
Classifier: License :: OSI Approved :: MIT License
License-File: LICENSE
Requires-Dist: httpx
Requires-Dist: defopt
Requires-Dist: packaging
Requires-Dist: wcwidth
Requires-Dist: pytest ; extra == "dev"
Requires-Dist: mypy ; extra == "dev"
Project-URL: Home, https://github.com/lordmauve/wheel_matrix
Provides-Extra: dev
